<!--
   This file contains a listing of public holidays for NSW in Australia
   for the years 2002-2005.
   - Steve [stephen@intense.com.au] (12/7/2002)
-->

<events>
 <event name="New Year's Day" type="public_holiday">
  <date day="1" month="1"></date>
 </event>
 <event name="Australia Day" type="public_holiday">
  <date day="26" month="1"></date>
 </event>
 <event name="Anzac Day" type="public_holiday">
  <date day="25" month="4"></date>
 </event>
 <event name="Good Friday" type="public_holiday">
  <date day="21" month="4" year="2000"></date>
  <date day="13" month="4" year="2001"></date>
  <date day="29" month="3" year="2002"></date>
  <date day="18" month="4" year="2003"></date>
  <date day="9" month="4" year="2004"></date>
  <date day="25" month="3" year="2005"></date>
 </event>
 <event name="Easter Monday" type="public_holiday">
  <date day="24" month="4" year="2000"></date>
  <date day="16" month="4" year="2001"></date>
  <date day="1" month="4" year="2002"></date>
  <date day="21" month="4" year="2003"></date>
  <date day="12" month="4" year="2004"></date>
  <date day="28" month="3" year="2005"></date>
 </event>
 <event name="Queen's Birthday" type="public_holiday">
  <date day="10" month="6" year="2002"></date>
  <date day="9" month="6" year="2003"></date>
  <date day="7" month="6" year="2004"></date>
  <date day="6" month="6" year="2005"></date>
 </event>
 <event name="Labour Day" type="public_holiday">
  <date day="7" month="10" year="2002"></date>
  <date day="6" month="10" year="2003"></date>
  <date day="4" month="10" year="2004"></date>
  <date day="3" month="10" year="2005"></date>
 </event>
 <event name="Christmas Day" type="public_holiday">
  <date day="25" month="12"></date>
 </event>
 <event name="Boxing Day" type="public_holiday">
  <date day="26" month="12"></date>
 </event>

</events>

