<search function="msdn">
  <name>Microsoft Developer Network (MSDN)</name>
  <description>Search for articles on the MSDN.<br/>
  "msdn ocx" or "msdn iframes /library"<br/>
  <a class="helpboxDescLabels">Switches:</a><br/>
	<table cellpadding="0" cellspacing="0" border="0">
		<tr><td class="helpboxDescColumns">/library</td><td class="helpboxDescColumns"> - </td><td class="helpboxDescColumns">Limits search to the MSDN Library.</td></tr>
	</table>
  </description>
  <category>Computers</category>
  <link>http://msdn.microsoft.com/</link>
  <contributor>Ryan Edwards</contributor>
  <form name="msdnf"
        action="http://msdn.microsoft.com/library/shared/searchtab/searchHandoff.asp" 
        method="get">
    <input type="hidden" id="qu" name="qu"/>
    <input type="hidden" name="handoffurl" value="/isapi/gosearch.asp?TARGET=/us/dev/default.asp"/>
    <input type="hidden" name="stcfg" value="/library/searchtabconfig.xml"/>
    <input type="hidden" Name="scopeid"/>
  </form>
  <script><![CDATA[
    function msdn(q)
    {
      var args = parseArgs(q, "library");
      if( q == "" )
        openSearchWindow("http://msdn.microsoft.com/");
      else if( args.switches.length == 1 && args.switches[0].name == "library" )
      {
        document.msdnf.scopeid.value = "2";
        document.msdnf.qu.value = args.q;
        submitForm( msdnf );
      }
      else
      {
        document.msdnf.scopeid.value = "1";
        document.msdnf.qu.value = args.q;
        submitForm( msdnf );
      }
    }
  ]]></script>
</search>