<search function="uns">
  <name>Word Unscrambler</name>
  <description>To calculate scrabble scores: "uns inourdnas"</description>
  <category>Fun</category>
  <link>http://www.concordance.com/unscrambler.htm</link>
  <form name="unsf"
        action="http://64.65.56.251/cgi-bin/unscrambler.pl"
        method="post">
    <input type="hidden" name="letters" value=""/>
  </form>
  <script><![CDATA[
    function uns(q)
    {
      if (q == "")
        openSearchWindow("http://www.concordance.com/unscrambler.htm");
      else
      {
        document.unsf.letters.value=q;
        submitForm(unsf);
      }
    }
  ]]></script>

  <copyright>
	Copyright (c) 2002 David Bau
	Distributed under the terms of the
	GNU Public License, Version 2 (http://www.gnu.org/copyleft/gpl.txt)
  </copyright>
</search>
